torchenhanced/__init__.py
torchenhanced/modules.py
torchenhanced/trainer.py
torchenhanced/ml/__init__.py
torchenhanced/ml/functional/__init__.py
torchenhanced/ml/functional/batch_roll.py
torchenhanced/ml/optim/__init__.py
torchenhanced/ml/optim/cosine_warmup.py
torchenhanced/util/__init__.py
torchenhanced/util/color_compression.py
torchenhanced/util/files.py
torchenhanced/util/misc.py
torchenhanced-0.3.5.dist-info/METADATA
torchenhanced-0.3.5.dist-info/WHEEL
torchenhanced-0.3.5.dist-info/top_level.txt
torchenhanced-0.3.5.dist-info/RECORD
