Metadata-Version: 2.4
Name: torchenhanced
Version: 0.3.5
Summary: Wrappers for pytorch stuff I use on the daily
Author-email: Vassilis Papadopoulos <frotaur@hotmail.co.uk>
License: MIT License
Project-URL: Homepage, https://github.com/frotaur/torchenhanced
Project-URL: Bug Tracker, https://github.com/frotaur/torchenhanced/issues
Classifier: Programming Language :: Python :: 3
Classifier: License :: OSI Approved :: MIT License
Classifier: Operating System :: OS Independent
Classifier: Development Status :: 3 - Alpha
Requires-Python: >=3.9
Requires-Dist: torch
Requires-Dist: torchvision
Requires-Dist: matplotlib
Requires-Dist: tqdm
Requires-Dist: wandb
Requires-Dist: opencv_python
Requires-Dist: numpy
Requires-Dist: Pillow
Requires-Dist: tqdm
